LICENSE.txt
MANIFEST.in
README.rst
setup.cfg
setup.py
clodsa/__init__.py
clodsa/augment.py
clodsa/command_line.py
clodsa/examples.py
clodsa/generate_sample.py
clodsa/keras_example.py
clodsa/mosaic.py
clodsa.egg-info/PKG-INFO
clodsa.egg-info/SOURCES.txt
clodsa.egg-info/dependency_links.txt
clodsa.egg-info/entry_points.txt
clodsa.egg-info/requires.txt
clodsa.egg-info/top_level.txt
clodsa/augmentors/__init__.py
clodsa/augmentors/augmentorFactory.py
clodsa/augmentors/augmentorsList.py
clodsa/augmentors/cocoLinearDetectionAugmentor.py
clodsa/augmentors/cocoLinearInstanceSegmentationAugmentor.py
clodsa/augmentors/cocoSequentialInstanceSegmentationAugmentor.py
clodsa/augmentors/folderKerasLinearClassificationAugmentor.py
clodsa/augmentors/folderKerasSemanticSegmentationAugmentor.py
clodsa/augmentors/folderLinearClassificationAugmentor.py
clodsa/augmentors/folderLinearSemanticSegmentationAugmentor.py
clodsa/augmentors/folderStackLinearSemanticSegmentationAugmentor.py
clodsa/augmentors/folderVideoLinearClassificationAugmentor.py
clodsa/augmentors/hdf5LinearClassificationAugmentor.py
clodsa/augmentors/hdf5LinearLocalizationAugmentor.py
clodsa/augmentors/hdf5LinearSegmentationAugmentor.py
clodsa/augmentors/hdf5PowerClassificationAugmentor.py
clodsa/augmentors/hdf5PowerSegmentationAugmentor.py
clodsa/augmentors/iaugmentor.py
clodsa/augmentors/jsonLinearInstanceSegmentationAugmentor.py
clodsa/augmentors/pascalVOCLinearDetectionAugmentor.py
clodsa/augmentors/pascalVOCLinearLocalizationAugmentor.py
clodsa/augmentors/yoloLinearDetectionAugmentor.py
clodsa/augmentors/youtubeVideoLinearDetectionAugmentor.py
clodsa/augmentors/utils/__init__.py
clodsa/augmentors/utils/aspectawarepreprocessor.py
clodsa/augmentors/utils/hdf5datasetwriter.py
clodsa/augmentors/utils/readCOCOJSON.py
clodsa/augmentors/utils/utils.py
clodsa/techniques/__init__.py
clodsa/techniques/averageBlurringAugmentationTechnique.py
clodsa/techniques/bilateralBlurringAugmentationTechnique.py
clodsa/techniques/blurringAugmentationTechnique.py
clodsa/techniques/changeToHSVAugmentationTechnique.py
clodsa/techniques/changeToLABAugmentationTechnique.py
clodsa/techniques/cropAugmentationTechnique.py
