Metadata-Version: 2.1
Name: clodsa
Version: 1.2.48
Summary: Image augmentation for classification, localization, detection and semantic segmentation
Home-page: https://github.com/joheras/CLoDSA
Author: Jonathan Heras
Author-email: joheras@gmail.com
Keywords: image augmentation,classification,localization,detection,semantic segmentation
Classifier: Development Status :: 4 - Beta
Classifier: Intended Audience :: Developers
Classifier: Topic :: Software Development :: Build Tools
Classifier: License :: OSI Approved :: MIT License
Classifier: Programming Language :: Python :: 2.7
Classifier: Programming Language :: Python :: 3.6
License-File: LICENSE.txt
